Metadata-Version: 1.1
Name: photo-namer-nautilus
Version: 0.0.6
Summary: Photo namer nautilus file manager script for files imported with CatGrab phpto import app.
Home-page: http://www.digital.elements.li
Author: Andreas Fritz, digital.elements.li
Author-email: photo-namer@projects.elements.li
License: UNKNOWN
Download-URL: https://pypi.python.org/pypi/photo-namer-nautilus
Keywords: photo namer script file manager nautilus thunar nemo
Platform: UNKNOWN
Classifier: Development Status :: 4 - Beta
Classifier: License :: OSI Approved :: MIT License
Classifier: Operating System :: Unix
Classifier: Programming Language :: Python :: 3
Classifier: Environment :: Console
Classifier: Natural Language :: English
Classifier: Intended Audience :: End Users/Desktop
Classifier: Topic :: Desktop Environment
Classifier: Topic :: Desktop Environment :: File Managers
Classifier: Topic :: Desktop Environment :: Gnome
